datapyrse/__init__.py
datapyrse/_entity.py
datapyrse/_entity_collection.py
datapyrse/_entity_metadata.py
datapyrse/_entity_reference.py
datapyrse/_entity_reference_collection.py
datapyrse/_service_client.py
datapyrse/py.typed
datapyrse/messages/__init__.py
datapyrse/messages/_associate.py
datapyrse/messages/_create.py
datapyrse/messages/_dataverse_request.py
datapyrse/messages/_delete.py
datapyrse/messages/_disassociate.py
datapyrse/messages/_methods.py
datapyrse/messages/_relate.py
datapyrse/messages/_retrieve.py
datapyrse/messages/_retrieve_multiple.py
datapyrse/messages/_update.py
datapyrse/query/__init__.py
datapyrse/query/_column_set.py
datapyrse/query/_condition_expression.py
datapyrse/query/_filter_expression.py
datapyrse/query/_link_entity.py
datapyrse/query/_option_set.py
datapyrse/query/_order_expression.py
datapyrse/query/_query_expression.py
datapyrse/utils/__init__.py
datapyrse/utils/_dataverse.py
tests/__init__.py
tests/models/__init__.py
tests/models/test_column_set.py
tests/models/test_condition_expression.py
tests/models/test_entity.py
tests/models/test_entity_collection.py
tests/models/test_entity_metadata.py
tests/models/test_entity_reference.py
tests/models/test_filter_expression.py
tests/models/test_link_entity.py
tests/models/test_option_set.py
tests/models/test_query_expression.py
tests/services/__init__.py
tests/services/test_create.py
tests/services/test_delete.py
tests/services/test_retrieve.py
tests/services/test_retrieve_multiple.py
tests/utils/__init__.py
tests/utils/test_dataverse_get_entity_metadata.py
tests/utils/test_dataverse_parse_entity_to_web_api_body.py
tests/utils/test_dataverse_transform_column_set.py
tests/utils/test_query_to_fetch.py
datapyrse-0.8.0.dist-info/LICENSE
datapyrse-0.8.0.dist-info/METADATA
datapyrse-0.8.0.dist-info/WHEEL
datapyrse-0.8.0.dist-info/top_level.txt
datapyrse-0.8.0.dist-info/RECORD
