Metadata-Version: 2.1
Name: datapyrse
Version: 0.8.0
Summary: A package used to mimic the functionality of the Dataverse SDK.
Author: Blake Bradford
License: MIT License
Project-URL: Homepage, https://github.com/blakeZTL/datapyrse
Keywords: Dataverse,Power Platform,Microsoft,SDK
Classifier: License :: OSI Approved :: MIT License
Classifier: Programming Language :: Python
Classifier: Programming Language :: Python :: 3
Requires-Python: >=3.12
License-File: LICENSE
Requires-Dist: certifi==2024.8.30
Requires-Dist: cffi==1.17.1
Requires-Dist: charset-normalizer==3.3.2
Requires-Dist: colorama==0.4.6
Requires-Dist: cryptography==43.0.1
Requires-Dist: idna==3.10
Requires-Dist: iniconfig==2.0.0
Requires-Dist: msal==1.31.0
Requires-Dist: packaging==24.1
Requires-Dist: pluggy==1.5.0
Requires-Dist: pycparser==2.22
Requires-Dist: PyJWT==2.9.0
Requires-Dist: requests==2.32.3
Requires-Dist: urllib3==2.2.3
Provides-Extra: dev
Requires-Dist: black; extra == "dev"
Requires-Dist: bumpver; extra == "dev"
Requires-Dist: pip-tools; extra == "dev"
Requires-Dist: pytest; extra == "dev"
Requires-Dist: setuptools; extra == "dev"
